MANIFEST.in
README.md
setup.py
xalglib/alglib316_64free.dll
xalglib/alglib316_64free.so
xalglib/xalglib.py
xalglib.egg-info/PKG-INFO
xalglib.egg-info/SOURCES.txt
xalglib.egg-info/dependency_links.txt
xalglib.egg-info/top_level.txt