Metadata-Version: 1.2
Name: xalglib
Version: 3.16.0
Summary: ALGLIB is a cross-platform numerical analysis and data processing library
Home-page: UNKNOWN
Author: ALGLIB
License: GNU General Public License v3 (GPLv3)
Platform: UNKNOWN
Classifier: Programming Language :: Python :: 3
Classifier: License :: OSI Approved :: GNU General Public License v3 (GPLv3)
Classifier: Operating System :: OS Independent
Requires-Python: >=3.6
